devmatch/__init__.py
devmatch/__main__.py
devmatch/auth.py
devmatch/cli.py
devmatch/config.py
devmatch/firebase_client.py
devmatch-0.1.0.dist-info/METADATA
devmatch-0.1.0.dist-info/WHEEL
devmatch-0.1.0.dist-info/entry_points.txt
devmatch-0.1.0.dist-info/top_level.txt
devmatch-0.1.0.dist-info/RECORD
