Metadata-Version: 2.4
Name: devmatch
Version: 0.1.0
Summary: A minimal developer collaborative platform client
Home-page: https://github.com/devmatch/devmatch-cli
Author: DevMatch Team
Author-email: DevMatch Team <team@devmatch.dev>
License: MIT
Project-URL: Homepage, https://github.com/devmatch/devmatch-cli
Project-URL: Bug Reports, https://github.com/devmatch/devmatch-cli/issues
Project-URL: Source, https://github.com/devmatch/devmatch-cli
Classifier: Development Status :: 3 - Alpha
Classifier: Intended Audience :: Developers
Classifier: License :: OSI Approved :: MIT License
Classifier: Operating System :: OS Independent
Classifier: Programming Language :: Python :: 3
Classifier: Programming Language :: Python :: 3.8
Classifier: Programming Language :: Python :: 3.9
Classifier: Programming Language :: Python :: 3.10
Classifier: Programming Language :: Python :: 3.11
Classifier: Programming Language :: Python :: 3.12
Requires-Python: >=3.8
Requires-Dist: typer>=0.9.0
Requires-Dist: rich>=13.0.0
Requires-Dist: requests>=2.25.0
Requires-Dist: firebase-admin>=6.0.0
Requires-Dist: python-dotenv>=0.19.0
Requires-Dist: setuptools>=75.3.2
Dynamic: author
Dynamic: home-page
Dynamic: requires-python
